pymywatertoronto/__init__.py
pymywatertoronto/const.py
pymywatertoronto/enums.py
pymywatertoronto/errors.py
pymywatertoronto/format_date.py
pymywatertoronto/mywatertoronto.py
pymywatertoronto-1.5.0.dist-info/LICENSE
pymywatertoronto-1.5.0.dist-info/METADATA
pymywatertoronto-1.5.0.dist-info/WHEEL
pymywatertoronto-1.5.0.dist-info/top_level.txt
pymywatertoronto-1.5.0.dist-info/RECORD
