Metadata-Version: 2.1
Name: pymywatertoronto
Version: 1.5.0
Summary: Library built for Home Assistant to integrate with the City of Toronto MyWaterToronto service
Author-email: MyWaterToronto <davepearce@live.com>
License: MIT License
Project-URL: Homepage, https://github.com/davecpearce/pymywatertoronto
Keywords: water,meter,cityoftoronto
Classifier: License :: OSI Approved :: MIT License
Classifier: Programming Language :: Python
Classifier: Programming Language :: Python :: 3
Requires-Python: >=3.11
License-File: LICENSE
Requires-Dist: aiohttp
Requires-Dist: aiohttp-retry
Requires-Dist: pytz
